win_tor_resources/__init__.py
win_tor_resources/win_tor_resources.py
win_tor_resources/Tor/libcrypto-1_1.dll
win_tor_resources/Tor/libevent-2-1-7.dll
win_tor_resources/Tor/libevent_core-2-1-7.dll
win_tor_resources/Tor/libevent_extra-2-1-7.dll
win_tor_resources/Tor/libgcc_s_dw2-1.dll
win_tor_resources/Tor/libssl-1_1.dll
win_tor_resources/Tor/libssp-0.dll
win_tor_resources/Tor/libwinpthread-1.dll
win_tor_resources/Tor/meek-client.exe
win_tor_resources/Tor/obfs4proxy.exe
win_tor_resources/Tor/snowflake-client.exe
win_tor_resources/Tor/tor.exe
win_tor_resources/Tor/zlib1.dll
win_tor_resources/Tor/Data/geoip
win_tor_resources/Tor/Data/geoip6
win_tor_resources-1.0.1.dist-info/LICENSE
win_tor_resources-1.0.1.dist-info/METADATA
win_tor_resources-1.0.1.dist-info/WHEEL
win_tor_resources-1.0.1.dist-info/top_level.txt
win_tor_resources-1.0.1.dist-info/RECORD
