Metadata-Version: 2.1
Name: win-tor-resources
Version: 1.0.1
Summary: Tor resources(binary) for python in windows
Home-page: https://github.com/jakbin
Author: Jak Bin
License: MIT License
Keywords: tor,windows,python,tor-binary
Platform: UNKNOWN
Classifier: Programming Language :: Python :: 3
Classifier: License :: OSI Approved :: MIT License
Classifier: Operating System :: Microsoft :: Windows
Requires-Python: >=3
License-File: LICENSE
